{"dataList":[{"id":0,"DID":"building_towncenter","name":"towncenter"},{"id":1,"DID":"building_farm","name":"farm"},{"id":2,"DID":"building_factory","name":"factory"},{"id":3,"DID":"building_filterationplant","name":"filterationplant"},{"id":4,"DID":"building_house","name":"house"},{"id":5,"DID":"TBD","name":"TBD"},{"id":6,"DID":"TBD","name":"TBD"},{"id":7,"DID":"TBD","name":"TBD"},{"id":8,"DID":"TBD","name":"TBD"},{"id":9,"DID":"TBD","name":"TBD"},{"id":10,"DID":"currency_gold","name":"gold"},{"id":11,"DID":"resource_food","name":"food"},{"id":12,"DID":"resource_wood","name":"wood"},{"id":13,"DID":"resource_stone","name":"stone"},{"id":14,"DID":"resource_metal","name":"metal"}]}
